{
    "tbp.monty": {
        "tbp_run": "{PY} {PROJECT_ROOT}/run.py experiment={EXPERIMENT_NAME}",
        "tbp_run_parallel": "{PY} {PROJECT_ROOT}/run_parallel.py experiment={EXPERIMENT_NAME}"
    },
    "feat.dynamic_resizing": {
        "tbp_run": "{PY} {PROJECT_ROOT}/run.py experiment={EXPERIMENT_NAME}",
        "tbp_run_parallel": "{PY} {PROJECT_ROOT}/run_parallel.py experiment={EXPERIMENT_NAME}"
    },
    "tbp.plot": {
        "tbp_run": "{PY} {PROJECT_ROOT}/src/tbp/plot/cli.py {PLOT_NAME} {RESULTS_DIR}"
    },
    "tbp.benchmarks": {
        "tbp_run": "{PY} {PROJECT_ROOT}/compare_benchmarks.py --baseline {BASELINE} --proposed {PROPOSED} --mode table",
        "tbp_run_parallel": "{PY} {PROJECT_ROOT}/compare_benchmarks.py --baseline {BASELINE} --proposed {PROPOSED} --mode plot"
    }
}
